orm_gen/__init__.py
orm_gen/main.py
ormgen/__init__.py
ormgen/main.py
ormgen/ormgen.py
ormgen-1.0.0.dist-info/METADATA
ormgen-1.0.0.dist-info/RECORD
ormgen-1.0.0.dist-info/WHEEL
ormgen-1.0.0.dist-info/entry_points.txt
ormgen-1.0.0.dist-info/top_level.txt
