Metadata-Version: 2.1
Name: ormgen
Version: 1.0.0
Summary: generate sqlalchemy orm class automatically from existing database
Home-page: https://github.com/irgb/ormgen
Author: UNKNOWN
Author-email: UNKNOWN
License: UNKNOWN
Platform: UNKNOWN
Requires-Dist: PyMySQL (>=0.7.11)
